precise_lite_runner/__init__.py
precise_lite_runner/params.py
precise_lite_runner/runner.py
precise_lite_runner/util.py
precise_lite_runner/vectorization.py
precise_lite_runner/version.py
precise_lite_runner-0.4.1.dist-info/LICENSE
precise_lite_runner-0.4.1.dist-info/METADATA
precise_lite_runner-0.4.1.dist-info/WHEEL
precise_lite_runner-0.4.1.dist-info/top_level.txt
precise_lite_runner-0.4.1.dist-info/RECORD
