Metadata-Version: 2.1
Name: precise-lite-runner
Version: 0.4.1
Summary: UNKNOWN
Home-page: https://github.com/OpenVoiceOS/precise_lite_runner
Author: jarbas
Author-email: jarbasai@mailfence.com
License: Apache-2.0
Platform: UNKNOWN
Requires-Dist: sonopy (==0.1.2)
Requires-Dist: pyaudio
Provides-Extra: full
Requires-Dist: tensorflow ; extra == 'full'
Provides-Extra: tflite
Requires-Dist: tflite-runtime ; extra == 'tflite'
